tests/__init__.py
tests/conftest.py
tests/test_file.py
tests/test_rows_and_cols.py
xlsxopera/Notebook.py
xlsxopera/__init__.py
xlsxopera-1.1.dist-info/LICENSE
xlsxopera-1.1.dist-info/METADATA
xlsxopera-1.1.dist-info/WHEEL
xlsxopera-1.1.dist-info/top_level.txt
xlsxopera-1.1.dist-info/RECORD
